pymetalog/__init__.py
pymetalog/a_vector.py
pymetalog/class_method.py
pymetalog/metalog.py
pymetalog/pdf_quantile_functions.py
pymetalog/support.py
pymetalog-0.2.2.dist-info/LICENSE
pymetalog-0.2.2.dist-info/METADATA
pymetalog-0.2.2.dist-info/WHEEL
pymetalog-0.2.2.dist-info/top_level.txt
pymetalog-0.2.2.dist-info/RECORD
