Metadata-Version: 2.1
Name: pymetalog
Version: 0.2.2
Summary: A python package that generates functions for the metalog distribution. The metalog distribution is a highly flexible probability distribution that can be used to model data without traditional parameters.
Home-page: https://github.com/tjefferies/pymetalog
Author: Colin Smith, Travis Jefferies, Isaac J. Faber
License: UNKNOWN
Download-URL: https://github.com/tjefferies/pymetalog/archive/0.2.2.tar.gz
Platform: UNKNOWN
Classifier: Programming Language :: Python :: 3
Classifier: License :: OSI Approved :: MIT License
Classifier: Operating System :: OS Independent
Requires-Dist: numpy
Requires-Dist: scipy
